novel_mcp/__init__.py
novel_mcp/main.py
novel_mcp-0.1.3.dist-info/METADATA
novel_mcp-0.1.3.dist-info/WHEEL
novel_mcp-0.1.3.dist-info/entry_points.txt
novel_mcp-0.1.3.dist-info/licenses/LICENSE
novel_mcp-0.1.3.dist-info/RECORD
