Metadata-Version: 2.4
Name: novel-mcp
Version: 0.1.3
Summary: A Model Context Protocol (MCP) server for novel processing with mathematical operations
Project-URL: Homepage, https://github.com/dingle123/novel-mcp
Project-URL: Repository, https://github.com/dingle123/novel-mcp.git
Project-URL: Issues, https://github.com/dingle123/novel-mcp/issues
Project-URL: Documentation, https://github.com/dingle123/novel-mcp#readme
Author-email: dingle <18911755085@163.com>
Maintainer-email: dingle <18911755085@163.com>
License-Expression: MIT
License-File: LICENSE
Keywords: ai,mcp,novel,protocol,server
Classifier: Development Status :: 3 - Alpha
Classifier: Intended Audience :: Developers
Classifier: License :: OSI Approved :: MIT License
Classifier: Programming Language :: Python :: 3
Classifier: Programming Language :: Python :: 3.10
Classifier: Programming Language :: Python :: 3.11
Classifier: Programming Language :: Python :: 3.12
Classifier: Topic :: Internet :: WWW/HTTP :: HTTP Servers
Classifier: Topic :: Software Development :: Libraries :: Python Modules
Requires-Python: >=3.10
Requires-Dist: mcp[cli]>=1.9.4
Provides-Extra: dev
Requires-Dist: black>=22.0; extra == 'dev'
Requires-Dist: flake8>=4.0; extra == 'dev'
Requires-Dist: isort>=5.0; extra == 'dev'
Requires-Dist: pytest>=7.0; extra == 'dev'
